excel_toolkit_for_py/__init__.py
excel_toolkit_for_py/advanced_features.py
excel_toolkit_for_py/conversions.py
excel_toolkit_for_py/data_analysis.py
excel_toolkit_for_py/exporters.py
excel_toolkit_for_py/reader.py
excel_toolkit_for_py/utils.py
excel_toolkit_for_py/validations.py
excel_toolkit_for_py/writer.py
excel_toolkit_for_py-1.4.0.dist-info/licenses/LICENSE
excel_toolkit_for_py-1.4.0.dist-info/METADATA
excel_toolkit_for_py-1.4.0.dist-info/WHEEL
excel_toolkit_for_py-1.4.0.dist-info/top_level.txt
excel_toolkit_for_py-1.4.0.dist-info/RECORD
