Metadata-Version: 2.4
Name: excel_toolkit_for_py
Version: 1.4.0
Summary: 📊 Facilite a leitura, manipulação, conversão, validação e exportação de arquivos Excel e CSV com Python.
Home-page: https://github.com/robertolima-dev/excel-toolkit-for-py
Author: Roberto Lima
Author-email: Roberto Lima <robertolima.izphera@gmail.com>
Project-URL: Homepage, https://github.com/robertolima-dev/excel-toolkit-for-py
Project-URL: Repository, https://github.com/robertolima-dev/excel-toolkit-for-py
Project-URL: Issues, https://github.com/robertolima-dev/excel-toolkit-for-py/issues
Classifier: Programming Language :: Python :: 3
Classifier: Programming Language :: Python :: 3.8
Classifier: Programming Language :: Python :: 3.9
Classifier: Programming Language :: Python :: 3.10
Classifier: Programming Language :: Python :: 3.11
Classifier: Programming Language :: Python :: 3.12
Classifier: Operating System :: OS Independent
Classifier: Intended Audience :: Developers
Classifier: Topic :: Software Development :: Libraries :: Python Modules
Classifier: Topic :: Scientific/Engineering :: Information Analysis
Requires-Python: >=3.8
License-File: LICENSE
Requires-Dist: pandas>=2.0.0
Requires-Dist: openpyxl>=3.1.0
Requires-Dist: msoffcrypto-tool>=5.1.1
Requires-Dist: xlrd>=2.0.1
Requires-Dist: xlwt>=1.3.0
Requires-Dist: weasyprint>=60.1
Requires-Dist: jinja2>=3.1.2
Requires-Dist: numpy>=1.21.0
Requires-Dist: scipy>=1.7.0
Provides-Extra: dev
Requires-Dist: pytest>=7.0.0; extra == "dev"
Requires-Dist: pytest-cov>=4.0.0; extra == "dev"
Requires-Dist: black>=23.0.0; extra == "dev"
Requires-Dist: flake8>=6.0.0; extra == "dev"
Requires-Dist: mypy>=1.0.0; extra == "dev"
Dynamic: author
Dynamic: home-page
Dynamic: license-file
Dynamic: requires-python
